{
    "transseq": [
        {
            "payment": {
                "amount": 113,
                "earned": 0,
                "receiver": "bob   ",
                "sender": "carol "
            },
            "time": 293066902.7623307
        },
        {
            "payment": {
                "amount": 26,
                "earned": 0,
                "receiver": "bob   ",
                "sender": "carol "
            },
            "time": 935037170.289133
        },
        {
            "payment": {
                "amount": 55,
                "earned": 0,
                "receiver": "bob   ",
                "sender": "alice "
            },
            "time": 1148446064.7747676
        },
        {
            "payment": {
                "amount": 10,
                "earned": 0,
                "receiver": "bob   ",
                "sender": "carol "
            },
            "time": 1285238571.6668327
        },
        {
            "payment": {
                "amount": 290,
                "earned": 0,
                "receiver": "carol ",
                "sender": "bob   "
            },
            "time": 1485489116.8073711
        },
        {
            "payment": {
                "amount": 41,
                "earned": 0,
                "receiver": "bob   ",
                "sender": "alice "
            },
            "time": 1723485373.409844
        },
        {
            "payment": {
                "amount": 96,
                "earned": 0,
                "receiver": "bob   ",
                "sender": "alice "
            },
            "time": 1807225414.204475
        },
        {
            "payment": {
                "amount": 333,
                "earned": 0,
                "receiver": "carol ",
                "sender": "0"
            },
            "time": 1807316643.2701366
        },
        {
            "payment": {
                "amount": 30,
                "earned": 0,
                "receiver": "bob   ",
                "sender": "carol "
            },
            "time": 2152452663.96397
        },
        {
            "payment": {
                "amount": 55,
                "earned": 0,
                "receiver": "bob   ",
                "sender": "alice "
            },
            "time": 2592110962.5961537
        },
        {
            "payment": {
                "amount": 173,
                "earned": 0,
                "receiver": "bob   ",
                "sender": "ted   "
            },
            "time": 2670361196.9178047
        },
        {
            "payment": {
                "amount": 401,
                "earned": 0,
                "receiver": "carol ",
                "sender": "bob   "
            },
            "time": 3064835893.4243517
        },
        {
            "payment": {
                "amount": 37,
                "earned": 0,
                "receiver": "bob   ",
                "sender": "carol "
            },
            "time": 3205857105.5825777
        },
        {
            "payment": {
                "amount": 147,
                "earned": 0,
                "receiver": "carol ",
                "sender": "bob   "
            },
            "time": 3442633549.339418
        },
        {
            "payment": {
                "amount": 10,
                "earned": 0,
                "receiver": "bob   ",
                "sender": "alice "
            },
            "time": 3443450992.0133905
        },
        {
            "payment": {
                "amount": 73,
                "earned": 0,
                "receiver": "bob   ",
                "sender": "carol "
            },
            "time": 3460163358.7935925
        },
        {
            "payment": {
                "amount": 81,
                "earned": 0,
                "receiver": "bob   ",
                "sender": "ted   "
            },
            "time": 3585309079.7180395
        },
        {
            "payment": {
                "amount": 37,
                "earned": 0,
                "receiver": "bob   ",
                "sender": "carol "
            },
            "time": 3720926798.841086
        },
        {
            "payment": {
                "amount": 649,
                "earned": 0,
                "receiver": "carol ",
                "sender": "0"
            },
            "time": 3727229265.9705772
        },
        {
            "payment": {
                "amount": 64,
                "earned": 0,
                "receiver": "bob   ",
                "sender": "carol "
            },
            "time": 3860287993.7370505
        },
        {
            "payment": {
                "amount": 67,
                "earned": 0,
                "receiver": "bob   ",
                "sender": "alice "
            },
            "time": 4235382559.261847
        },
        {
            "payment": {
                "amount": 126,
                "earned": 0,
                "receiver": "0",
                "sender": "alice "
            },
            "time": 4318369457.340356
        },
        {
            "payment": {
                "amount": 370,
                "earned": 0,
                "receiver": "0",
                "sender": "bob   "
            },
            "time": 4404789090.355844
        },
        {
            "payment": {
                "amount": 125,
                "earned": 0,
                "receiver": "bob   ",
                "sender": "ted   "
            },
            "time": 4751571962.779128
        },
        {
            "payment": {
                "amount": 151,
                "earned": 0,
                "receiver": "0",
                "sender": "ted   "
            },
            "time": 4870124624.810538
        },
        {
            "payment": {
                "amount": 795,
                "earned": 0,
                "receiver": "bob   ",
                "sender": "0"
            },
            "time": 5439356199.31908
        },
        {
            "payment": {
                "amount": 1,
                "earned": 0,
                "receiver": "carol ",
                "sender": "0"
            },
            "time": 5610728711.982771
        },
        {
            "payment": {
                "amount": 53,
                "earned": 0,
                "receiver": "bob   ",
                "sender": "alice "
            },
            "time": 5765634113.843667
        },
        {
            "payment": {
                "amount": 37,
                "earned": 0,
                "receiver": "bob   ",
                "sender": "carol "
            },
            "time": 5907563752.166182
        },
        {
            "payment": {
                "amount": 37,
                "earned": 0,
                "receiver": "bob   ",
                "sender": "carol "
            },
            "time": 6125047331.793919
        },
        {
            "payment": {
                "amount": 274,
                "earned": 0,
                "receiver": "0",
                "sender": "ted   "
            },
            "time": 6129080771.706767
        },
        {
            "payment": {
                "amount": 792,
                "earned": 0,
                "receiver": "carol ",
                "sender": "bob   "
            },
            "time": 6397349100.365693
        },
        {
            "payment": {
                "amount": 1026,
                "earned": 0,
                "receiver": "carol ",
                "sender": "bob   "
            },
            "time": 6514798917.659107
        },
        {
            "payment": {
                "amount": 85,
                "earned": 0,
                "receiver": "bob   ",
                "sender": "alice "
            },
            "time": 6557565681.092123
        },
        {
            "payment": {
                "amount": 17,
                "earned": 0,
                "receiver": "bob   ",
                "sender": "carol "
            },
            "time": 6767017599.320721
        },
        {
            "payment": {
                "amount": 71,
                "earned": 0,
                "receiver": "bob   ",
                "sender": "alice "
            },
            "time": 7087814156.069639
        },
        {
            "payment": {
                "amount": 511,
                "earned": 0,
                "receiver": "0",
                "sender": "carol "
            },
            "time": 7172253208.573954
        },
        {
            "payment": {
                "amount": 1336,
                "earned": 0,
                "receiver": "carol ",
                "sender": "alice "
            },
            "time": 7283150648.834856
        },
        {
            "payment": {
                "amount": 2012,
                "earned": 0,
                "receiver": "carol ",
                "sender": "ted   "
            },
            "time": 7631861198.480753
        },
        {
            "payment": {
                "amount": 38,
                "earned": 0,
                "receiver": "bob   ",
                "sender": "carol "
            },
            "time": 7823143025.336748
        },
        {
            "payment": {
                "amount": 37,
                "earned": 0,
                "receiver": "bob   ",
                "sender": "carol "
            },
            "time": 8234867694.8970585
        },
        {
            "payment": {
                "amount": 287,
                "earned": 0,
                "receiver": "0",
                "sender": "bob   "
            },
            "time": 8267832571.412816
        },
        {
            "payment": {
                "amount": 68,
                "earned": 0,
                "receiver": "bob   ",
                "sender": "alice "
            },
            "time": 8585361363.547481
        },
        {
            "payment": {
                "amount": 30,
                "earned": 0,
                "receiver": "bob   ",
                "sender": "carol "
            },
            "time": 8787611130.212679
        },
        {
            "payment": {
                "amount": 398,
                "earned": 0,
                "receiver": "carol ",
                "sender": "bob   "
            },
            "time": 8812319279.570469
        },
        {
            "payment": {
                "amount": 37,
                "earned": 0,
                "receiver": "bob   ",
                "sender": "carol "
            },
            "time": 9041891641.791262
        },
        {
            "payment": {
                "amount": 83,
                "earned": 0,
                "receiver": "bob   ",
                "sender": "alice "
            },
            "time": 9042351805.951666
        },
        {
            "payment": {
                "amount": 888,
                "earned": 0,
                "receiver": "0",
                "sender": "alice "
            },
            "time": 9484512372.388817
        },
        {
            "payment": {
                "amount": 18,
                "earned": 0,
                "receiver": "bob   ",
                "sender": "carol "
            },
            "time": 9977100982.876785
        },
        {
            "payment": {
                "amount": 37,
                "earned": 0,
                "receiver": "bob   ",
                "sender": "carol "
            },
            "time": 10122398084.569174
        },
        {
            "payment": {
                "amount": 835,
                "earned": 0,
                "receiver": "carol ",
                "sender": "bob   "
            },
            "time": 10242784032.55838
        },
        {
            "payment": {
                "amount": 57,
                "earned": 0,
                "receiver": "bob   ",
                "sender": "alice "
            },
            "time": 10246596260.954025
        },
        {
            "payment": {
                "amount": 27,
                "earned": 0,
                "receiver": "bob   ",
                "sender": "carol "
            },
            "time": 10493566090.003553
        },
        {
            "payment": {
                "amount": 442,
                "earned": 0,
                "receiver": "carol ",
                "sender": "0"
            },
            "time": 10779347386.182722
        },
        {
            "payment": {
                "amount": 2926,
                "earned": 0,
                "receiver": "carol ",
                "sender": "alice "
            },
            "time": 10913718453.10907
        },
        {
            "payment": {
                "amount": 37,
                "earned": 0,
                "receiver": "bob   ",
                "sender": "carol "
            },
            "time": 10934397200.014694
        },
        {
            "payment": {
                "amount": 88,
                "earned": 0,
                "receiver": "0",
                "sender": "ted   "
            },
            "time": 11093870877.775703
        },
        {
            "payment": {
                "amount": 113,
                "earned": 0,
                "receiver": "bob   ",
                "sender": "ted   "
            },
            "time": 11216076792.342064
        },
        {
            "payment": {
                "amount": 287,
                "earned": 0,
                "receiver": "0",
                "sender": "bob   "
            },
            "time": 11546427596.780632
        },
        {
            "payment": {
                "amount": 119,
                "earned": 0,
                "receiver": "bob   ",
                "sender": "alice "
            },
            "time": 11561321051.71696
        },
        {
            "payment": {
                "amount": 84,
                "earned": 0,
                "receiver": "bob   ",
                "sender": "carol "
            },
            "time": 11614912967.64521
        },
        {
            "payment": {
                "amount": 57,
                "earned": 0,
                "receiver": "bob   ",
                "sender": "alice "
            },
            "time": 11757636990.218103
        },
        {
            "payment": {
                "amount": 37,
                "earned": 0,
                "receiver": "bob   ",
                "sender": "carol "
            },
            "time": 12262300894.242985
        },
        {
            "payment": {
                "amount": 58,
                "earned": 0,
                "receiver": "bob   ",
                "sender": "alice "
            },
            "time": 12773622005.88265
        },
        {
            "payment": {
                "amount": 96,
                "earned": 0,
                "receiver": "bob   ",
                "sender": "carol "
            },
            "time": 13120177128.64698
        },
        {
            "payment": {
                "amount": 69,
                "earned": 0,
                "receiver": "bob   ",
                "sender": "alice "
            },
            "time": 13837596852.197145
        },
        {
            "payment": {
                "amount": 265,
                "earned": 0,
                "receiver": "carol ",
                "sender": "bob   "
            },
            "time": 13844281981.866756
        },
        {
            "payment": {
                "amount": 2,
                "earned": 0,
                "receiver": "bob   ",
                "sender": "carol "
            },
            "time": 13951693523.806852
        },
        {
            "payment": {
                "amount": 172,
                "earned": 0,
                "receiver": "bob   ",
                "sender": "ted   "
            },
            "time": 14063163344.729404
        },
        {
            "payment": {
                "amount": 202,
                "earned": 0,
                "receiver": "carol ",
                "sender": "0"
            },
            "time": 14411034554.668337
        },
        {
            "payment": {
                "amount": 350,
                "earned": 0,
                "receiver": "0",
                "sender": "ted   "
            },
            "time": 14758795210.462202
        },
        {
            "payment": {
                "amount": 39,
                "earned": 0,
                "receiver": "bob   ",
                "sender": "carol "
            },
            "time": 14870237361.514538
        },
        {
            "payment": {
                "amount": 2338,
                "earned": 0,
                "receiver": "carol ",
                "sender": "ted   "
            },
            "time": 15054545891.449553
        },
        {
            "payment": {
                "amount": 507,
                "earned": 0,
                "receiver": "carol ",
                "sender": "bob   "
            },
            "time": 15232101746.26066
        },
        {
            "payment": {
                "amount": 46,
                "earned": 0,
                "receiver": "bob   ",
                "sender": "alice "
            },
            "time": 15232554266.610115
        },
        {
            "payment": {
                "amount": 463,
                "earned": 0,
                "receiver": "bob   ",
                "sender": "0"
            },
            "time": 15585223611.740953
        },
        {
            "payment": {
                "amount": 578,
                "earned": 0,
                "receiver": "0",
                "sender": "bob   "
            },
            "time": 15746634943.121113
        },
        {
            "payment": {
                "amount": 37,
                "earned": 0,
                "receiver": "bob   ",
                "sender": "carol "
            },
            "time": 15856498368.098213
        },
        {
            "payment": {
                "amount": 226,
                "earned": 0,
                "receiver": "0",
                "sender": "alice "
            },
            "time": 15884049507.364183
        },
        {
            "payment": {
                "amount": 72,
                "earned": 0,
                "receiver": "bob   ",
                "sender": "carol "
            },
            "time": 16083396631.825958
        },
        {
            "payment": {
                "amount": 59,
                "earned": 0,
                "receiver": "bob   ",
                "sender": "alice "
            },
            "time": 16375780059.463554
        },
        {
            "payment": {
                "amount": 465,
                "earned": 0,
                "receiver": "carol ",
                "sender": "bob   "
            },
            "time": 16588393051.46649
        },
        {
            "payment": {
                "amount": 188,
                "earned": 0,
                "receiver": "bob   ",
                "sender": "ted   "
            },
            "time": 16732694176.92216
        },
        {
            "payment": {
                "amount": 101,
                "earned": 0,
                "receiver": "bob   ",
                "sender": "ted   "
            },
            "time": 17342817610.13308
        },
        {
            "payment": {
                "amount": 37,
                "earned": 0,
                "receiver": "bob   ",
                "sender": "carol "
            },
            "time": 17395827210.459705
        },
        {
            "payment": {
                "amount": 42,
                "earned": 0,
                "receiver": "bob   ",
                "sender": "alice "
            },
            "time": 17597410698.748463
        },
        {
            "payment": {
                "amount": 10,
                "earned": 0,
                "receiver": "bob   ",
                "sender": "carol "
            },
            "time": 17994575139.614407
        },
        {
            "payment": {
                "amount": 83,
                "earned": 0,
                "receiver": "0",
                "sender": "alice "
            },
            "time": 18339429091.613697
        },
        {
            "payment": {
                "amount": 125,
                "earned": 0,
                "receiver": "bob   ",
                "sender": "alice "
            },
            "time": 18389342265.996918
        },
        {
            "payment": {
                "amount": 378,
                "earned": 0,
                "receiver": "carol ",
                "sender": "0"
            },
            "time": 18414127060.471985
        },
        {
            "payment": {
                "amount": 351,
                "earned": 0,
                "receiver": "0",
                "sender": "carol "
            },
            "time": 18448775256.85995
        },
        {
            "payment": {
                "amount": 44,
                "earned": 0,
                "receiver": "bob   ",
                "sender": "carol "
            },
            "time": 18636545407.14121
        },
        {
            "payment": {
                "amount": 106,
                "earned": 0,
                "receiver": "bob   ",
                "sender": "alice "
            },
            "time": 19181273833.24537
        },
        {
            "payment": {
                "amount": 119,
                "earned": 0,
                "receiver": "bob   ",
                "sender": "carol "
            },
            "time": 19278515674.66801
        },
        {
            "payment": {
                "amount": 287,
                "earned": 0,
                "receiver": "0",
                "sender": "bob   "
            },
            "time": 19410735878.863438
        },
        {
            "payment": {
                "amount": 949,
                "earned": 0,
                "receiver": "carol ",
                "sender": "alice "
            },
            "time": 19519491387.733524
        },
        {
            "payment": {
                "amount": 102,
                "earned": 0,
                "receiver": "bob   ",
                "sender": "alice "
            },
            "time": 19527684017.45777
        },
        {
            "payment": {
                "amount": 163,
                "earned": 0,
                "receiver": "bob   ",
                "sender": "carol "
            },
            "time": 19601677639.33114
        },
        {
            "payment": {
                "amount": 551,
                "earned": 0,
                "receiver": "carol ",
                "sender": "0"
            },
            "time": 19801241159.94897
        },
        {
            "payment": {
                "amount": 331,
                "earned": 0,
                "receiver": "0",
                "sender": "ted   "
            },
            "time": 19976665397.633396
        },
        {
            "payment": {
                "amount": 69,
                "earned": 0,
                "receiver": "bob   ",
                "sender": "carol "
            },
            "time": 20709129470.621853
        },
        {
            "payment": {
                "amount": 212,
                "earned": 0,
                "receiver": "0",
                "sender": "alice "
            },
            "time": 20709788661.08097
        },
        {
            "payment": {
                "amount": 154,
                "earned": 0,
                "receiver": "bob   ",
                "sender": "ted   "
            },
            "time": 21002249781.104103
        },
        {
            "payment": {
                "amount": 88,
                "earned": 0,
                "receiver": "bob   ",
                "sender": "alice "
            },
            "time": 21022793634.741554
        },
        {
            "payment": {
                "amount": 151,
                "earned": 0,
                "receiver": "carol ",
                "sender": "bob   "
            },
            "time": 21350037996.191494
        },
        {
            "payment": {
                "amount": 208,
                "earned": 0,
                "receiver": "carol ",
                "sender": "0"
            },
            "time": 21644838025.874275
        },
        {
            "payment": {
                "amount": 31,
                "earned": 0,
                "receiver": "bob   ",
                "sender": "carol "
            },
            "time": 21942029593.97969
        },
        {
            "payment": {
                "amount": 130,
                "earned": 0,
                "receiver": "0",
                "sender": "ted   "
            },
            "time": 21975341183.764633
        },
        {
            "payment": {
                "amount": 69,
                "earned": 0,
                "receiver": "bob   ",
                "sender": "alice "
            },
            "time": 22552924499.923187
        },
        {
            "payment": {
                "amount": 1973,
                "earned": 0,
                "receiver": "carol ",
                "sender": "ted   "
            },
            "time": 22724122906.636395
        },
        {
            "payment": {
                "amount": 44,
                "earned": 0,
                "receiver": "bob   ",
                "sender": "alice "
            },
            "time": 23271304322.954998
        },
        {
            "payment": {
                "amount": 48,
                "earned": 0,
                "receiver": "bob   ",
                "sender": "carol "
            },
            "time": 23534464805.897038
        },
        {
            "payment": {
                "amount": 37,
                "earned": 0,
                "receiver": "bob   ",
                "sender": "carol "
            },
            "time": 23542433999.884308
        },
        {
            "payment": {
                "amount": 453,
                "earned": 0,
                "receiver": "carol ",
                "sender": "bob   "
            },
            "time": 23989773764.204716
        },
        {
            "payment": {
                "amount": 397,
                "earned": 0,
                "receiver": "carol ",
                "sender": "0"
            },
            "time": 24270570204.382652
        },
        {
            "payment": {
                "amount": 587,
                "earned": 0,
                "receiver": "0",
                "sender": "alice "
            },
            "time": 24508293006.228348
        },
        {
            "payment": {
                "amount": 131,
                "earned": 0,
                "receiver": "bob   ",
                "sender": "carol "
            },
            "time": 24620123388.839764
        },
        {
            "payment": {
                "amount": 92,
                "earned": 0,
                "receiver": "bob   ",
                "sender": "alice "
            },
            "time": 24668517339.617264
        },
        {
            "payment": {
                "amount": 1361,
                "earned": 0,
                "receiver": "carol ",
                "sender": "alice "
            },
            "time": 25155237564.761322
        },
        {
            "payment": {
                "amount": 96,
                "earned": 0,
                "receiver": "bob   ",
                "sender": "carol "
            },
            "time": 25262093656.366566
        },
        {
            "payment": {
                "amount": 644,
                "earned": 0,
                "receiver": "carol ",
                "sender": "bob   "
            },
            "time": 25593700228.45607
        },
        {
            "payment": {
                "amount": 44,
                "earned": 0,
                "receiver": "0",
                "sender": "bob   "
            },
            "time": 25906137629.00467
        },
        {
            "payment": {
                "amount": 65,
                "earned": 0,
                "receiver": "bob   ",
                "sender": "carol "
            },
            "time": 25981710475.058945
        },
        {
            "payment": {
                "amount": 425,
                "earned": 0,
                "receiver": "0",
                "sender": "ted   "
            },
            "time": 25992546944.128983
        },
        {
            "payment": {
                "amount": 72,
                "earned": 0,
                "receiver": "bob   ",
                "sender": "alice "
            },
            "time": 26251160579.561012
        },
        {
            "payment": {
                "amount": 52,
                "earned": 0,
                "receiver": "bob   ",
                "sender": "alice "
            },
            "time": 26584295267.79578
        },
        {
            "payment": {
                "amount": 301,
                "earned": 0,
                "receiver": "bob   ",
                "sender": "0"
            },
            "time": 26634367691.89193
        },
        {
            "payment": {
                "amount": 21,
                "earned": 0,
                "receiver": "bob   ",
                "sender": "carol "
            },
            "time": 26700213426.617313
        },
        {
            "payment": {
                "amount": 382,
                "earned": 0,
                "receiver": "carol ",
                "sender": "bob   "
            },
            "time": 26978004422.067642
        },
        {
            "payment": {
                "amount": 489,
                "earned": 0,
                "receiver": "carol ",
                "sender": "0"
            },
            "time": 27090699756.417786
        },
        {
            "payment": {
                "amount": 120,
                "earned": 0,
                "receiver": "0",
                "sender": "ted   "
            },
            "time": 27241909128.27119
        },
        {
            "payment": {
                "amount": 189,
                "earned": 0,
                "receiver": "bob   ",
                "sender": "ted   "
            },
            "time": 27434243060.757412
        },
        {
            "payment": {
                "amount": 26,
                "earned": 0,
                "receiver": "bob   ",
                "sender": "carol "
            },
            "time": 27744475873.85343
        },
        {
            "payment": {
                "amount": 109,
                "earned": 0,
                "receiver": "bob   ",
                "sender": "alice "
            },
            "time": 28120766877.277386
        },
        {
            "payment": {
                "amount": 396,
                "earned": 0,
                "receiver": "carol ",
                "sender": "0"
            },
            "time": 28636302368.484875
        },
        {
            "payment": {
                "amount": 574,
                "earned": 0,
                "receiver": "carol ",
                "sender": "bob   "
            },
            "time": 28638079880.550976
        },
        {
            "payment": {
                "amount": 43,
                "earned": 0,
                "receiver": "bob   ",
                "sender": "alice "
            },
            "time": 28764476952.390125
        },
        {
            "payment": {
                "amount": 81,
                "earned": 0,
                "receiver": "bob   ",
                "sender": "alice "
            },
            "time": 28860551621.42517
        },
        {
            "payment": {
                "amount": 212,
                "earned": 0,
                "receiver": "0",
                "sender": "alice "
            },
            "time": 28904449121.781734
        },
        {
            "payment": {
                "amount": 22,
                "earned": 0,
                "receiver": "bob   ",
                "sender": "carol "
            },
            "time": 29195263227.339325
        },
        {
            "payment": {
                "amount": 247,
                "earned": 0,
                "receiver": "0",
                "sender": "ted   "
            },
            "time": 30209273434.155975
        },
        {
            "payment": {
                "amount": 2175,
                "earned": 0,
                "receiver": "carol ",
                "sender": "ted   "
            },
            "time": 30211419775.89445
        },
        {
            "payment": {
                "amount": 61,
                "earned": 0,
                "receiver": "bob   ",
                "sender": "alice "
            },
            "time": 30377374531.134384
        },
        {
            "payment": {
                "amount": 240,
                "earned": 0,
                "receiver": "0",
                "sender": "alice "
            },
            "time": 30430599792.284695
        },
        {
            "payment": {
                "amount": 59,
                "earned": 0,
                "receiver": "bob   ",
                "sender": "carol "
            },
            "time": 30553584763.36526
        },
        {
            "payment": {
                "amount": 58,
                "earned": 0,
                "receiver": "bob   ",
                "sender": "alice "
            },
            "time": 30593763824.189823
        },
        {
            "payment": {
                "amount": 136,
                "earned": 0,
                "receiver": "bob   ",
                "sender": "ted   "
            },
            "time": 30726609562.573658
        },
        {
            "payment": {
                "amount": 37,
                "earned": 0,
                "receiver": "bob   ",
                "sender": "carol "
            },
            "time": 30869183718.451736
        },
        {
            "payment": {
                "amount": 49,
                "earned": 0,
                "receiver": "bob   ",
                "sender": "alice "
            },
            "time": 31188643527.44175
        },
        {
            "payment": {
                "amount": 132,
                "earned": 0,
                "receiver": "carol ",
                "sender": "0"
            },
            "time": 31220812402.4514
        },
        {
            "payment": {
                "amount": 40,
                "earned": 0,
                "receiver": "0",
                "sender": "alice "
            },
            "time": 31334126008.040184
        },
        {
            "payment": {
                "amount": 506,
                "earned": 0,
                "receiver": "carol ",
                "sender": "bob   "
            },
            "time": 31344674202.54932
        },
        {
            "payment": {
                "amount": 43,
                "earned": 0,
                "receiver": "bob   ",
                "sender": "carol "
            },
            "time": 32083587439.678467
        },
        {
            "payment": {
                "amount": 686,
                "earned": 0,
                "receiver": "0",
                "sender": "bob   "
            },
            "time": 32219300673.412945
        },
        {
            "payment": {
                "amount": 40,
                "earned": 0,
                "receiver": "bob   ",
                "sender": "alice "
            },
            "time": 32650748762.547344
        },
        {
            "payment": {
                "amount": 662,
                "earned": 0,
                "receiver": "carol ",
                "sender": "bob   "
            },
            "time": 32700965507.75515
        },
        {
            "payment": {
                "amount": 243,
                "earned": 0,
                "receiver": "bob   ",
                "sender": "0"
            },
            "time": 32818284016.103783
        },
        {
            "payment": {
                "amount": 25,
                "earned": 0,
                "receiver": "bob   ",
                "sender": "carol "
            },
            "time": 33060735389.929092
        },
        {
            "payment": {
                "amount": 296,
                "earned": 0,
                "receiver": "0",
                "sender": "ted   "
            },
            "time": 33176637740.040752
        },
        {
            "payment": {
                "amount": 33,
                "earned": 0,
                "receiver": "bob   ",
                "sender": "alice "
            },
            "time": 33442680329.7958
        },
        {
            "payment": {
                "amount": 717,
                "earned": 0,
                "receiver": "carol ",
                "sender": "bob   "
            },
            "time": 33609797521.60908
        },
        {
            "payment": {
                "amount": 110,
                "earned": 0,
                "receiver": "bob   ",
                "sender": "ted   "
            },
            "time": 33660121589.527435
        },
        {
            "payment": {
                "amount": 73,
                "earned": 0,
                "receiver": "bob   ",
                "sender": "carol "
            },
            "time": 33696532624.70856
        },
        {
            "payment": {
                "amount": 71,
                "earned": 0,
                "receiver": "bob   ",
                "sender": "carol "
            },
            "time": 33791641339.19015
        },
        {
            "payment": {
                "amount": 166,
                "earned": 0,
                "receiver": "bob   ",
                "sender": "carol "
            },
            "time": 34114276267.291645
        },
        {
            "payment": {
                "amount": 385,
                "earned": 0,
                "receiver": "0",
                "sender": "ted   "
            },
            "time": 34193732881.11055
        },
        {
            "payment": {
                "amount": 87,
                "earned": 0,
                "receiver": "bob   ",
                "sender": "alice "
            },
            "time": 34234611897.044254
        },
        {
            "payment": {
                "amount": 37,
                "earned": 0,
                "receiver": "bob   ",
                "sender": "carol "
            },
            "time": 34252832514.630653
        },
        {
            "payment": {
                "amount": 39,
                "earned": 0,
                "receiver": "carol ",
                "sender": "0"
            },
            "time": 34901198708.229675
        },
        {
            "payment": {
                "amount": 825,
                "earned": 0,
                "receiver": "carol ",
                "sender": "bob   "
            },
            "time": 34966088826.81491
        },
        {
            "payment": {
                "amount": 681,
                "earned": 0,
                "receiver": "0",
                "sender": "alice "
            },
            "time": 35301404378.53977
        },
        {
            "payment": {
                "amount": 36,
                "earned": 0,
                "receiver": "bob   ",
                "sender": "carol "
            },
            "time": 35416895320.00726
        },
        {
            "payment": {
                "amount": 2872,
                "earned": 0,
                "receiver": "carol ",
                "sender": "alice "
            },
            "time": 36151817269.62722
        },
        {
            "payment": {
                "amount": 277,
                "earned": 0,
                "receiver": "carol ",
                "sender": "bob   "
            },
            "time": 36322380132.02074
        },
        {
            "payment": {
                "amount": 36,
                "earned": 0,
                "receiver": "bob   ",
                "sender": "alice "
            },
            "time": 36339818778.62094
        },
        {
            "payment": {
                "amount": 241,
                "earned": 0,
                "receiver": "carol ",
                "sender": "bob   "
            },
            "time": 36352532548.68617
        },
        {
            "payment": {
                "amount": 47,
                "earned": 0,
                "receiver": "carol ",
                "sender": "0"
            },
            "time": 36626567780.96826
        },
        {
            "payment": {
                "amount": 65,
                "earned": 0,
                "receiver": "0",
                "sender": "ted   "
            },
            "time": 36808657558.14294
        },
        {
            "payment": {
                "amount": 119,
                "earned": 0,
                "receiver": "bob   ",
                "sender": "ted   "
            },
            "time": 36827921178.37485
        },
        {
            "payment": {
                "amount": 37,
                "earned": 0,
                "receiver": "bob   ",
                "sender": "carol "
            },
            "time": 37023034296.484085
        },
        {
            "payment": {
                "amount": 37,
                "earned": 0,
                "receiver": "bob   ",
                "sender": "carol "
            },
            "time": 37070457865.46471
        },
        {
            "payment": {
                "amount": 62,
                "earned": 0,
                "receiver": "bob   ",
                "sender": "alice "
            },
            "time": 37131750345.8694
        },
        {
            "payment": {
                "amount": 440,
                "earned": 0,
                "receiver": "carol ",
                "sender": "bob   "
            },
            "time": 37723089126.566154
        },
        {
            "payment": {
                "amount": 37,
                "earned": 0,
                "receiver": "bob   ",
                "sender": "carol "
            },
            "time": 37767588667.1244
        },
        {
            "payment": {
                "amount": 1713,
                "earned": 0,
                "receiver": "carol ",
                "sender": "ted   "
            },
            "time": 37993790993.693245
        },
        {
            "payment": {
                "amount": 485,
                "earned": 0,
                "receiver": "carol ",
                "sender": "bob   "
            },
            "time": 38109793556.61634
        },
        {
            "payment": {
                "amount": 450,
                "earned": 0,
                "receiver": "0",
                "sender": "carol "
            },
            "time": 38121320997.20341
        },
        {
            "payment": {
                "amount": 54,
                "earned": 0,
                "receiver": "bob   ",
                "sender": "alice "
            },
            "time": 38412810272.476166
        },
        {
            "payment": {
                "amount": 30,
                "earned": 0,
                "receiver": "bob   ",
                "sender": "carol "
            },
            "time": 38776082558.41057
        },
        {
            "payment": {
                "amount": 438,
                "earned": 0,
                "receiver": "0",
                "sender": "bob   "
            },
            "time": 38818655087.88927
        },
        {
            "payment": {
                "amount": 63,
                "earned": 0,
                "receiver": "bob   ",
                "sender": "alice "
            },
            "time": 39063999252.25223
        },
        {
            "payment": {
                "amount": 63,
                "earned": 0,
                "receiver": "bob   ",
                "sender": "carol "
            },
            "time": 39418052825.93736
        },
        {
            "payment": {
                "amount": 594,
                "earned": 0,
                "receiver": "carol ",
                "sender": "0"
            },
            "time": 39706934662.17065
        },
        {
            "payment": {
                "amount": 93,
                "earned": 0,
                "receiver": "bob   ",
                "sender": "alice "
            },
            "time": 39855930819.50069
        },
        {
            "payment": {
                "amount": 24,
                "earned": 0,
                "receiver": "bob   ",
                "sender": "carol "
            },
            "time": 40121879597.37995
        },
        {
            "payment": {
                "amount": 1893,
                "earned": 0,
                "receiver": "carol ",
                "sender": "alice "
            },
            "time": 40354529757.01214
        },
        {
            "payment": {
                "amount": 158,
                "earned": 0,
                "receiver": "bob   ",
                "sender": "ted   "
            },
            "time": 40596962528.96588
        },
        {
            "payment": {
                "amount": 52,
                "earned": 0,
                "receiver": "bob   ",
                "sender": "carol "
            },
            "time": 40783962900.218666
        },
        {
            "payment": {
                "amount": 89,
                "earned": 0,
                "receiver": "bob   ",
                "sender": "alice "
            },
            "time": 40891432563.280235
        },
        {
            "payment": {
                "amount": 161,
                "earned": 0,
                "receiver": "0",
                "sender": "ted   "
            },
            "time": 41021812673.04074
        },
        {
            "payment": {
                "amount": 163,
                "earned": 0,
                "receiver": "carol ",
                "sender": "bob   "
            },
            "time": 41070758805.19455
        },
        {
            "payment": {
                "amount": 638,
                "earned": 0,
                "receiver": "0",
                "sender": "alice "
            },
            "time": 41401103799.3164
        },
        {
            "payment": {
                "amount": 51,
                "earned": 0,
                "receiver": "bob   ",
                "sender": "carol "
            },
            "time": 41606772191.11353
        },
        {
            "payment": {
                "amount": 341,
                "earned": 0,
                "receiver": "carol ",
                "sender": "0"
            },
            "time": 41760616567.38489
        },
        {
            "payment": {
                "amount": 642,
                "earned": 0,
                "receiver": "carol ",
                "sender": "bob   "
            },
            "time": 41860128461.25675
        },
        {
            "payment": {
                "amount": 56,
                "earned": 0,
                "receiver": "bob   ",
                "sender": "alice "
            },
            "time": 42105827205.96023
        },
        {
            "payment": {
                "amount": 15,
                "earned": 0,
                "receiver": "bob   ",
                "sender": "carol "
            },
            "time": 42299046818.44132
        },
        {
            "payment": {
                "amount": 81,
                "earned": 0,
                "receiver": "bob   ",
                "sender": "ted   "
            },
            "time": 42479473641.46408
        },
        {
            "payment": {
                "amount": 79,
                "earned": 0,
                "receiver": "bob   ",
                "sender": "carol "
            },
            "time": 42617890551.791145
        },
        {
            "payment": {
                "amount": 85,
                "earned": 0,
                "receiver": "bob   ",
                "sender": "alice "
            },
            "time": 42897758773.20869
        },
        {
            "payment": {
                "amount": 90,
                "earned": 0,
                "receiver": "carol ",
                "sender": "bob   "
            },
            "time": 43090047530.19436
        },
        {
            "payment": {
                "amount": 40,
                "earned": 0,
                "receiver": "bob   ",
                "sender": "carol "
            },
            "time": 43158070320.97006
        },
        {
            "payment": {
                "amount": 177,
                "earned": 0,
                "receiver": "carol ",
                "sender": "0"
            },
            "time": 43604626578.83443
        },
        {
            "payment": {
                "amount": 51,
                "earned": 0,
                "receiver": "bob   ",
                "sender": "alice "
            },
            "time": 43628682038.844696
        },
        {
            "payment": {
                "amount": 20,
                "earned": 0,
                "receiver": "bob   ",
                "sender": "carol "
            },
            "time": 44014504786.88565
        },
        {
            "payment": {
                "amount": 244,
                "earned": 0,
                "receiver": "carol ",
                "sender": "bob   "
            },
            "time": 44446338835.40019
        },
        {
            "payment": {
                "amount": 78,
                "earned": 0,
                "receiver": "bob   ",
                "sender": "ted   "
            },
            "time": 44766464157.36609
        },
        {
            "payment": {
                "amount": 47,
                "earned": 0,
                "receiver": "bob   ",
                "sender": "alice "
            },
            "time": 45377297626.1046
        },
        {
            "payment": {
                "amount": 48,
                "earned": 0,
                "receiver": "bob   ",
                "sender": "alice "
            },
            "time": 45569104169.30861
        },
        {
            "payment": {
                "amount": 797,
                "earned": 0,
                "receiver": "carol ",
                "sender": "bob   "
            },
            "time": 45802630140.60602
        },
        {
            "payment": {
                "amount": 279,
                "earned": 0,
                "receiver": "carol ",
                "sender": "0"
            },
            "time": 45941294973.371895
        },
        {
            "payment": {
                "amount": 574,
                "earned": 0,
                "receiver": "carol ",
                "sender": "0"
            },
            "time": 46777035925.30317
        },
        {
            "payment": {
                "amount": 25,
                "earned": 0,
                "receiver": "bob   ",
                "sender": "alice "
            },
            "time": 46853206999.93153
        },
        {
            "payment": {
                "amount": 49,
                "earned": 0,
                "receiver": "bob   ",
                "sender": "alice "
            },
            "time": 47645138567.17999
        },
        {
            "payment": {
                "amount": 80,
                "earned": 0,
                "receiver": "carol ",
                "sender": "bob   "
            },
            "time": 50279162022.637505
        },
        {
            "payment": {
                "amount": 2174,
                "earned": 0,
                "receiver": "carol ",
                "sender": "alice "
            },
            "time": 52544790428.43121
        }
    ]
}